Projeto 1/Questões/Questão 5/Comparador_8bits.v
module Comparador_4bits (output wire G, L, E, input G_IN, input L_IN, input E_IN, input wire [3:0] A, B);

    assign G = (A > B) || ((A == B) && G_IN);
    assign L = (A < B) || ((A == B) && L_IN);
    assign E = ((A == B) && E_IN);

endmodule

module Comparador_8bits (output wire G, L, E, input wire [7:0] A, B);

    wire G_old, L_old, E_old;
    Comparador_4bits c1(G_old, L_old, E_old, 1'b0, 1'b0, 1'b1, A[3:0], B[3:0]);
  	Comparador_4bits c2(G, L, E, G_old, L_old, E_old, A[7:4], B[7:4]);

endmodule

Projeto 1/Questões/Questão 5/stimulus.v
module stimulus;
	// Inputs
	reg [7:0] A;
	reg [7:0] B;

	// Outputs
	wire G;
	wire L; 
	wire E;

	// Instantiate the Unit Under Test (UUT)
	Comparador_8bits uut (
		.A(A),
		.B(B),
		.G(G),
		.L(L),
		.E(E)
	);

	initial begin
		$dumpfile ("waves.vcd");
		$dumpvars (0, stimulus);
		// Initialize Inputs
		A = 8'b10000000;
		B = 8'b10000000;
	
		#20 A = 8'b11111111; 
		#20 B = 8'b11111111;
		#20 A = 8'b10000000;	
		#20 B = 8'b10000000;
		#20 A = 8'b11111111; 
		#20 B = 8'b11111111;
		#20 A = 8'b10000000;	
		#20 B = 8'b10000000;
		#20 A = 8'b11111111; 
		#20 B = 8'b11111111;
		#20 A = 8'b10000000;	
		#20 B = 8'b10000000;
		#20 A = 8'b11111111; 
		#20 B = 8'b11111111;
		#20 A = 8'b10000000;	
		#20 B = 8'b10000000;
		
		$finish;	
	end  
 
	initial begin
		$monitor ("T=%3d A=%d,B=%d,G=%d L=%d E=%d \n", $time, A, B, G, L, E);
	end
 
endmodule

Projeto 1/Questões/Questão 5/waves.vcd
$date
	Fri Mar 19 17:38:31 2021
$end
$version
	Icarus Verilog
$end
$timescale
	1s
$end
$scope module stimulus $end
$var wire 1 ! L $end
$var wire 1 " G $end
$var wire 1 # E $end
$var reg 8 $ A [7:0] $end
$var reg 8 % B [7:0] $end
$scope module uut $end
$var wire 8 & A [7:0] $end
$var wire 8 ' B [7:0] $end
$var wire 1 ( L_old $end
$var wire 1 ! L $end
$var wire 1 ) G_old $end
$var wire 1 " G $end
$var wire 1 * E_old $end
$var wire 1 # E $end
$scope module c1 $end
$var wire 4 + A [3:0] $end
$var wire 4 , B [3:0] $end
$var wire 1 * E $end
$var wire 1 - E_IN $end
$var wire 1 ) G $end
$var wire 1 . G_IN $end
$var wire 1 ( L $end
$var wire 1 / L_IN $end
$upscope $end
$scope module c2 $end
$var wire 4 0 A [3:0] $end
$var wire 4 1 B [3:0] $end
$var wire 1 # E $end
$var wire 1 * E_IN $end
$var wire 1 " G $end
$var wire 1 ) G_IN $end
$var wire 1 ! L $end
$var wire 1 ( L_IN $end
$upscope $end
$upscope $end
$upscope $end
$enddefinitions $end
#0
$dumpvars
b1000 1
b1000 0
0/
0.
1-
b0 ,
b0 +
1*
0)
0(
b10000000 '
b10000000 &
b10000000 %
b10000000 $
1#
0"
0!
$end
#20
1)
0*
1"
0#
b1111 +
b1111 0
b11111111 $
b11111111 &
#40
0"
1#
0)
1*
b1111 ,
b1111 1
b11111111 %
b11111111 '
#60
1(
0*
1!
0#
b0 +
b1000 0
b10000000 $
b10000000 &
#80
0!
1#
0(
1*
b0 ,
b1000 1
b10000000 %
b10000000 '
#100
1)
0*
1"
0#
b1111 +
b1111 0
b11111111 $
b11111111 &
#120
0"
1#
0)
1*
b1111 ,
b1111 1
b11111111 %
b11111111 '
#140
1(
0*
1!
0#
b0 +
b1000 0
b10000000 $
b10000000 &
#160
0!
1#
0(
1*
b0 ,
b1000 1
b10000000 %
b10000000 '
#180
1)
0*
1"
0#
b1111 +
b1111 0
b11111111 $
b11111111 &
#200
0"
1#
0)
1*
b1111 ,
b1111 1
b11111111 %
b11111111 '
#220
1(
0*
1!
0#
b0 +
b1000 0
b10000000 $
b10000000 &
#240
0!
1#
0(
1*
b0 ,
b1000 1
b10000000 %
b10000000 '
#260
1)
0*
1"
0#
b1111 +
b1111 0
b11111111 $
b11111111 &
#280
0"
1#
0)
1*
b1111 ,
b1111 1
b11111111 %
b11111111 '
#300
1(
0*
1!
0#
b0 +
b1000 0
b10000000 $
b10000000 &
#320
0!
1#
0(
1*
b0 ,
b1000 1
b10000000 %
b10000000 '
